ipp_utils/__init__.py
ipp_utils/_ipp_utils.py
ipp_utils/normalize_rfft.dll
ipp_utils/normalize_rfft.so
ipp_utils-2.0.0a1.dist-info/METADATA
ipp_utils-2.0.0a1.dist-info/WHEEL
ipp_utils-2.0.0a1.dist-info/top_level.txt
ipp_utils-2.0.0a1.dist-info/RECORD
