Metadata-Version: 2.1
Name: ipp-utils
Version: 2.0.0a1
Summary: Utils for Intel® Integrated Performance Primitives
Home-page: UNKNOWN
Author: veennn
Author-email: veennn@proton.com
License: MIT
Platform: UNKNOWN
Classifier: Development Status :: 3 - Alpha
Classifier: Programming Language :: Python :: 3
Classifier: License :: OSI Approved :: MIT License
Classifier: Operating System :: Microsoft :: Windows
Classifier: Operating System :: POSIX
Classifier: Operating System :: POSIX :: Linux
Requires-Python: >=3.8.0
Requires-Dist: scipy
Requires-Dist: ipp-devel
Requires-Dist: ipp
Requires-Dist: ipp-include
